hedge_sql/__init__.py
hedge_sql/hedge_sql.py
hedgesql-2.0.0.dist-info/METADATA
hedgesql-2.0.0.dist-info/WHEEL
hedgesql-2.0.0.dist-info/top_level.txt
hedgesql-2.0.0.dist-info/RECORD
