Metadata-Version: 2.1
Name: hedgesql
Version: 2.0.0
Summary: Convenient work with sqlite3 and aiosqlite
Author: HedgeDev
Author-email: hedge_dev@mail.ru
Classifier: Development Status :: 4 - Beta
Classifier: Intended Audience :: Developers
Classifier: Programming Language :: Python :: 3.6
Classifier: Programming Language :: Python :: 3.7
Classifier: Programming Language :: Python :: 3.8
Classifier: Programming Language :: Python :: 3.9
Classifier: Programming Language :: Python :: 3.10
Classifier: Programming Language :: Python :: 3.11
Requires-Python: >=3.6
Requires-Dist: aiosqlite
Requires-Dist: sqlite3
